{"updated":"2026-07-02T03:21:12.758Z","leads":[{"id":"node750467834","name":"Freedom Market","cuisine":"","addr":"1901 New Hampshire Avenue Northwest","phone":"+1 202-483-5526","social":0,"lat":38.9157515,"lon":-77.0374169},{"id":"node940939711","name":"InfoShop World Bank Group","cuisine":"","addr":"1776 Pennsylvania Avenue Northwest Washington","phone":"+1 202-458-4500","social":0,"lat":38.8992259,"lon":-77.0413581},{"id":"node2776113714","name":"Nicole's Flowers","cuisine":"","addr":"630","phone":"+1-703-548-5604","social":0,"lat":38.8116545,"lon":-77.0458192},{"id":"node2776114743","name":"Lideta Market","cuisine":"","addr":"1607 South Glebe Road","phone":"+1 703-920-3099","social":0,"lat":38.8560635,"lon":-77.0888422},{"id":"node3737366557","name":"Chelsea Market & Deli","cuisine":"","addr":"","phone":"+1 703-750-2448","social":0,"lat":38.8899434,"lon":-77.0856959},{"id":"node4085798290","name":"Jolie Jeweleries","cuisine":"","addr":"1754 Columbia Road Northwest Washington","phone":"+1 202-319-2881","social":0,"lat":38.9237099,"lon":-77.0407406},{"id":"node7546757957","name":"Steven's Shop","cuisine":"","addr":"6178 Arlington Boulevard Falls Church","phone":"+1-703-237-9535","social":0,"lat":38.8702819,"lon":-77.1469566},{"id":"node701594825","name":"Manhattan Market","cuisine":"","addr":"2647 Connecticut Avenue Northwest","phone":"","social":0,"lat":38.9249001,"lon":-77.0519964},{"id":"node734353614","name":"Beharry Jewelers","cuisine":"","addr":"710 14th Street Northwest","phone":"","social":0,"lat":38.898768,"lon":-77.03224},{"id":"node734374075","name":"New York Convenience","cuisine":"","addr":"","phone":"","social":0,"lat":38.8993189,"lon":-77.0328651},{"id":"node734412683","name":"Go Green","cuisine":"","addr":"","phone":"","social":0,"lat":38.901023,"lon":-77.032101},{"id":"node737066316","name":"Virginia Market","cuisine":"","addr":"1776 U Street Northwest","phone":"","social":0,"lat":38.9167673,"lon":-77.0411555},{"id":"node737066448","name":"Argonne Market","cuisine":"","addr":"1629 Columbia Road Northwest","phone":"","social":0,"lat":38.9264696,"lon":-77.0373262},{"id":"node737066567","name":"Colombia Market","cuisine":"","addr":"1733 Columbia Road Northwest Washington","phone":"","social":0,"lat":38.9245758,"lon":-77.0401525},{"id":"node737526124","name":"Glover Park Market","cuisine":"","addr":"2411 37th Street Northwest","phone":"","social":0,"lat":38.9214761,"lon":-77.0729046},{"id":"node737526129","name":"Novel Grocery","cuisine":"","addr":"4000 Tunlaw Road Northwest","phone":"","social":0,"lat":38.9252843,"lon":-77.080244},{"id":"node737526168","name":"Westchester Market","cuisine":"","addr":"4000 Cathedral Avenue Northwest","phone":"","social":0,"lat":38.9282709,"lon":-77.0799458},{"id":"node738194986","name":"1500 Market","cuisine":"","addr":"1500 Massachusetts Avenue Northwest","phone":"","social":0,"lat":38.9064403,"lon":-77.0356465},{"id":"node738195009","name":"DC Souvenirs","cuisine":"","addr":"1131 14th Street Northwest","phone":"","social":0,"lat":38.9047008,"lon":-77.031677},{"id":"node739339895","name":"Oasis","cuisine":"","addr":"2024 P Street Northwest","phone":"","social":0,"lat":38.9094669,"lon":-77.0460371},{"id":"node739528076","name":"Best Vending II","cuisine":"","addr":"730 21st Street Northwest","phone":"","social":0,"lat":38.8992996,"lon":-77.0469123},{"id":"node739528118","name":"Federal Market","cuisine":"","addr":"1215 23rd Street Northwest","phone":"","social":0,"lat":38.9059619,"lon":-77.0497934},{"id":"node739528206","name":"Marvelous Market","cuisine":"","addr":"2424 Pennsylvania Avenue Northwest","phone":"","social":0,"lat":38.9029778,"lon":-77.0518338},{"id":"node740272396","name":"Wisemillers Grocery & Deli","cuisine":"","addr":"1236 36th Street Northwest","phone":"","social":0,"lat":38.9063259,"lon":-77.0704123},{"id":"node740272422","name":"Le Petite Corner Store","cuisine":"","addr":"1643 34th Street Northwest","phone":"","social":0,"lat":38.9116137,"lon":-77.0676767},{"id":"node740272478","name":"Sara's Food Market","cuisine":"","addr":"3008 Q Street Northwest","phone":"","social":0,"lat":38.9103543,"lon":-77.0596779},{"id":"node750432407","name":"Town Square Gourmet","cuisine":"","addr":"4418 MacArthur Boulevard Northwest","phone":"","social":0,"lat":38.9068509,"lon":-77.0819789},{"id":"node750432418","name":"Mac Market & Deli","cuisine":"","addr":"5185 MacArthur Boulevard Northwest","phone":"","social":0,"lat":38.9268148,"lon":-77.1029112},{"id":"node750432421","name":"Palisades Deli & Market","cuisine":"","addr":"4554 MacArthur Boulevard Northwest","phone":"","social":0,"lat":38.9090713,"lon":-77.0875351},{"id":"node750467905","name":"U Mini Mart","cuisine":"","addr":"1351 U Street Northwest","phone":"","social":0,"lat":38.9171672,"lon":-77.0311031},{"id":"node768973109","name":"Georgetown Tees","cuisine":"","addr":"1075 Wisconsin Avenue Northwest","phone":"","social":0,"lat":38.9047518,"lon":-77.0626293},{"id":"node804047818","name":"Jennifer Convertables","cuisine":"","addr":"1634 Wisconsin Avenue Northwest","phone":"","social":0,"lat":38.9116706,"lon":-77.0657956},{"id":"node804074469","name":"English Rose Garden","cuisine":"","addr":"3209 O Street Northwest","phone":"","social":0,"lat":38.9079633,"lon":-77.0640361},{"id":"node804597942","name":"Reiters / Washington Law & Professional Books","cuisine":"","addr":"1900 G Street Northwest","phone":"","social":0,"lat":38.8981605,"lon":-77.0438609},{"id":"node804627275","name":"Market Of Columbia Plaza","cuisine":"","addr":"516 23rd Street Northwest","phone":"","social":0,"lat":38.8965266,"lon":-77.0511415},{"id":"node806589459","name":"Fleurgreige","cuisine":"","addr":"1653 Wisconsin Avenue Northwest","phone":"","social":0,"lat":38.9117979,"lon":-77.0654511},{"id":"node806606941","name":"Scheele's Market","cuisine":"","addr":"1331 29th Street Northwest","phone":"","social":0,"lat":38.9078075,"lon":-77.0579857},{"id":"node929764953","name":"Capital Image","cuisine":"","addr":"","phone":"","social":0,"lat":38.8522694,"lon":-77.0423477},{"id":"node945269130","name":"Wilson Florist","cuisine":"","addr":"","phone":"","social":0,"lat":38.895545,"lon":-77.070566},{"id":"node1218539035","name":"Georgetown University Bookstore","cuisine":"","addr":"","phone":"","social":0,"lat":38.9099326,"lon":-77.0744081},{"id":"node1728370922","name":"Russian Gourmet","cuisine":"","addr":"Slaters Ln","phone":"","social":0,"lat":38.8215526,"lon":-77.0478164},{"id":"node2112767332","name":"Raul's Mens Wear","cuisine":"","addr":"","phone":"","social":0,"lat":38.8048409,"lon":-77.0461495},{"id":"node2134010234","name":"Hoya Snaxa","cuisine":"","addr":"","phone":"","social":0,"lat":38.9072255,"lon":-77.0755587},{"id":"node2484163138","name":"Towers Food & Dry Cleaning","cuisine":"","addr":"1600 South Eads Street Arlington","phone":"","social":0,"lat":38.8578671,"lon":-77.0546831},{"id":"node2636164135","name":"Off Broadway Shoe Warehouse","cuisine":"","addr":"6302 Seven Corners Center Falls Church","phone":"","social":0,"lat":38.8697939,"lon":-77.1526098},{"id":"node2776114414","name":"El Paisa Grocery","cuisine":"","addr":"","phone":"","social":0,"lat":38.8362408,"lon":-77.0615268},{"id":"node2778688811","name":"24express Food Store","cuisine":"","addr":"","phone":"","social":0,"lat":38.8427613,"lon":-77.0634984},{"id":"node2778778861","name":"Gold Works by David Martin","cuisine":"","addr":"","phone":"","social":0,"lat":38.8059512,"lon":-77.0547903},{"id":"node2793770901","name":"The Neighborhoods DC","cuisine":"","addr":"","phone":"","social":0,"lat":38.8541921,"lon":-77.0433315},{"id":"node2806227486","name":"Today's News","cuisine":"","addr":"","phone":"","social":0,"lat":38.8971402,"lon":-77.0310058},{"id":"node3010511233","name":"Love Notes Gifts","cuisine":"","addr":"","phone":"","social":0,"lat":38.897955,"lon":-77.040324},{"id":"node3278391409","name":"River Place Market","cuisine":"","addr":"","phone":"","social":0,"lat":38.8927712,"lon":-77.0692542},{"id":"node3416858768","name":"Kiko's Shoe Shine","cuisine":"","addr":"","phone":"","social":0,"lat":38.9005282,"lon":-77.0453681},{"id":"node3505937110","name":"Fashion K City","cuisine":"","addr":"","phone":"","social":0,"lat":38.8368948,"lon":-77.0625903},{"id":"node3665177327","name":"Room & Board","cuisine":"","addr":"","phone":"","social":0,"lat":38.9153696,"lon":-77.0321806},{"id":"node3963159296","name":"Courthouse Place Gourmet","cuisine":"","addr":"","phone":"","social":0,"lat":38.889103,"lon":-77.085502},{"id":"node4070365490","name":"Because Science","cuisine":"","addr":"1759 Columbia Road Northwest Washington","phone":"","social":0,"lat":38.923751,"lon":-77.0414241},{"id":"node4075190289","name":"Martin Luther King, Jr. Memorial Bookstore","cuisine":"","addr":"West Basin Drive Southwest","phone":"","social":0,"lat":38.8863669,"lon":-77.0452137},{"id":"node4085796190","name":"Henry Jewelers","cuisine":"","addr":"","phone":"","social":0,"lat":38.923628,"lon":-77.0409009},{"id":"node4089003594","name":"Pórtico Bookstore IDB","cuisine":"","addr":"","phone":"","social":0,"lat":38.8993315,"lon":-77.0314932},{"id":"node4103696691","name":"Diener Jewlers","cuisine":"","addr":"","phone":"","social":0,"lat":38.9046836,"lon":-77.0432153},{"id":"node4677509710","name":"BM Boutique","cuisine":"","addr":"","phone":"","social":0,"lat":38.8037821,"lon":-77.1331128},{"id":"node4812035417","name":"DC Variedades","cuisine":"","addr":"3114 Mount Pleasant Street Northwest Washington","phone":"","social":0,"lat":38.9293097,"lon":-77.0378041},{"id":"node4822032789","name":"Tín Hành","cuisine":"","addr":"Wilson Boulevard Falls Church","phone":"","social":0,"lat":38.8729924,"lon":-77.1545897},{"id":"node4822032791","name":"Kim Hoàng Jewelry","cuisine":"","addr":"Wilson Boulevard Falls Church","phone":"","social":0,"lat":38.872983,"lon":-77.1546433},{"id":"node4822032793","name":"Kim Thư","cuisine":"","addr":"Wilson Boulevard Falls Church","phone":"","social":0,"lat":38.8729632,"lon":-77.1547587},{"id":"node4827970068","name":"Thiên Hỷ Gift Shop","cuisine":"","addr":"6795 Wilson Boulevard Falls Church","phone":"","social":0,"lat":38.8729958,"lon":-77.1549586},{"id":"node4827970075","name":"Linh Gems","cuisine":"","addr":"Wilson Boulevard Falls Church","phone":"","social":0,"lat":38.8731555,"lon":-77.1547856},{"id":"node4828079168","name":"Ngọc Quyên","cuisine":"","addr":"Wilson Boulevard Falls Church","phone":"","social":0,"lat":38.873239,"lon":-77.1545576},{"id":"node4828125272","name":"Bạch Tuyết","cuisine":"","addr":"Wilson Boulevard Falls Church","phone":"","social":0,"lat":38.8743325,"lon":-77.1539603},{"id":"node4828174975","name":"Ngoc Linh Jewelry","cuisine":"","addr":"6763 Wilson Boulevard Falls Church","phone":"","social":0,"lat":38.8742458,"lon":-77.1547441},{"id":"node4828174978","name":"Ngọc Hương Jewelry","cuisine":"","addr":"6763 Wilson Boulevard Falls Church","phone":"","social":0,"lat":38.8743502,"lon":-77.1546905},{"id":"node4828428334","name":"Hong Kong Fashions","cuisine":"","addr":"Wilson Boulevard Falls Church","phone":"","social":0,"lat":38.8738188,"lon":-77.1514155},{"id":"node5414988164","name":"Mediterranean Bakery and Cafe","cuisine":"","addr":"352 South Pickett Street Alexandria","phone":"","social":0,"lat":38.807522,"lon":-77.1239322},{"id":"node5556437474","name":"Pen & Prose Express","cuisine":"","addr":"","phone":"","social":0,"lat":38.8560778,"lon":-77.0427147},{"id":"node5924762918","name":"Penzeys Spices","cuisine":"","addr":"","phone":"","social":0,"lat":38.8867227,"lon":-77.1784847},{"id":"node6052771207","name":"Natural Cafe market & deli","cuisine":"","addr":"","phone":"","social":0,"lat":38.8808572,"lon":-77.1102685},{"id":"node6127384932","name":"Goldsmith Lambros, Inc","cuisine":"","addr":"7137 Little River Turnpike Annandale","phone":"","social":0,"lat":38.8293782,"lon":-77.1922033},{"id":"node6139435216","name":"Belmont Jewelers","cuisine":"","addr":"","phone":"","social":0,"lat":38.8628308,"lon":-77.0604082},{"id":"node6139435218","name":"Intissimi","cuisine":"","addr":"","phone":"","social":0,"lat":38.8629,"lon":-77.0604055},{"id":"node6233990292","name":"Hooray For Books","cuisine":"","addr":"","phone":"","social":0,"lat":38.8064167,"lon":-77.0566499},{"id":"node6245900411","name":"Ink by Hudson","cuisine":"","addr":"","phone":"","social":0,"lat":38.8528286,"lon":-77.0429792},{"id":"node6410526201","name":"CTY","cuisine":"","addr":"","phone":"","social":0,"lat":38.8483647,"lon":-77.0422214},{"id":"node6410526203","name":"CIBO Express","cuisine":"","addr":"","phone":"","social":0,"lat":38.8483406,"lon":-77.0426184},{"id":"node6942961843","name":"Rioja Market","cuisine":"","addr":"","phone":"","social":0,"lat":38.9219805,"lon":-77.0430692},{"id":"node7546757968","name":"Fashion City","cuisine":"","addr":"Arlington Boulevard Falls Church","phone":"","social":0,"lat":38.869778,"lon":-77.1476662},{"id":"node7557413890","name":"El Oasis Libreria Cristiana","cuisine":"","addr":"2930 Patrick Henry Drive Falls Church","phone":"","social":0,"lat":38.8704984,"lon":-77.1468856},{"id":"node7557413891","name":"Centro Market","cuisine":"","addr":"2930 Patrick Henry Drive Falls Church","phone":"","social":0,"lat":38.8705387,"lon":-77.1469645},{"id":"node9672799603","name":"Hamilton's Sofa & Leather Gallery","cuisine":"","addr":"5857 Leesburg Pike Falls Church","phone":"","social":0,"lat":38.8513102,"lon":-77.1322841},{"id":"node9708343530","name":"K&G","cuisine":"","addr":"Columbia Pike Falls Church","phone":"","social":0,"lat":38.8494836,"lon":-77.1322868},{"id":"node10588988004","name":"After Hours Tuxedo Rental","cuisine":"","addr":"2715 Wilson Boulevard","phone":"","social":0,"lat":38.8895905,"lon":-77.0911058}]}